{
    "swagger": "2.0",
    "info": {
        "description": "This is a sample server for user management.",
        "title": "Swagger Example API",
        "termsOfService": "http://swagger.io/terms/",
        "contact": {
            "name": "API Support",
            "url": "http://www.swagger.io/support",
            "email": "support@swagger.io"
        },
        "license": {
            "name": "Apache 2.0",
            "url": "http://www.apache.org/licenses/LICENSE-2.0.html"
        },
        "version": "1.0"
    },
    "host": "localhost:8880",
    "basePath": "/api/v1",
    "paths": {
        "/api/v1/OperationLogList": {
            "get": {
                "description": "操作日志分页查询",
                "consumes": [
                    "application/json"
                ],
                "produces": [
                    "application/json"
                ],
                "tags": [
                    "系统模块"
                ],
                "summary": "操作日志分页查询接口",
                "parameters": [
                    {
                        "type": "integer",
                        "description": "当前页",
                        "name": "currentPage",
                        "in": "query"
                    },
                    {
                        "type": "string",
                        "name": "ip",
                        "in": "query"
                    },
                    {
                        "type": "string",
                        "name": "operation_at",
                        "in": "query"
                    },
                    {
                        "type": "integer",
                        "description": "每页条数",
                        "name": "pageSize",
                        "in": "query"
                    },
                    {
                        "type": "string",
                        "name": "user_id",
                        "in": "query"
                    },
                    {
                        "type": "string",
                        "name": "user_name",
                        "in": "query"
                    }
                ],
                "responses": {
                    "200": {
                        "description": "OK",
                        "schema": {
                            "$ref": "#/definitions/github_com_Struggle-Rabbit_CampusLogistics_pkg_utils.SuccessResponse"
                        }
                    },
                    "400": {
                        "description": "Bad Request",
                        "schema": {
                            "$ref": "#/definitions/github_com_Struggle-Rabbit_CampusLogistics_pkg_utils.ErrResponse"
                        }
                    }
                }
            }
        },
        "/api/v1/login": {
            "post": {
                "description": "登录系统",
                "consumes": [
                    "application/json"
                ],
                "produces": [
                    "application/json"
                ],
                "tags": [
                    "用户管理"
                ],
                "summary": "用户登录接口",
                "parameters": [
                    {
                        "description": "入参",
                        "name": "data",
                        "in": "body",
                        "required": true,
                        "schema": {
                            "$ref": "#/definitions/github_com_Struggle-Rabbit_CampusLogistics_api_dto.LoginReq"
                        }
                    }
                ],
                "responses": {
                    "200": {
                        "description": "OK",
                        "schema": {
                            "$ref": "#/definitions/github_com_Struggle-Rabbit_CampusLogistics_pkg_utils.SuccessResponse"
                        }
                    },
                    "400": {
                        "description": "Bad Request",
                        "schema": {
                            "$ref": "#/definitions/github_com_Struggle-Rabbit_CampusLogistics_pkg_utils.ErrResponse"
                        }
                    }
                }
            }
        },
        "/api/v1/menu/add": {
            "post": {
                "description": "菜单创建",
                "consumes": [
                    "application/json"
                ],
                "produces": [
                    "application/json"
                ],
                "tags": [
                    "系统模块"
                ],
                "summary": "菜单创建接口",
                "parameters": [
                    {
                        "description": "入参",
                        "name": "data",
                        "in": "body",
                        "required": true,
                        "schema": {
                            "$ref": "#/definitions/github_com_Struggle-Rabbit_CampusLogistics_api_dto.CreateMenuReq"
                        }
                    }
                ],
                "responses": {
                    "200": {
                        "description": "OK",
                        "schema": {
                            "$ref": "#/definitions/github_com_Struggle-Rabbit_CampusLogistics_pkg_utils.SuccessResponse"
                        }
                    },
                    "400": {
                        "description": "Bad Request",
                        "schema": {
                            "$ref": "#/definitions/github_com_Struggle-Rabbit_CampusLogistics_pkg_utils.ErrResponse"
                        }
                    }
                }
            }
        },
        "/api/v1/menu/del": {
            "post": {
                "description": "菜单删除",
                "consumes": [
                    "application/json"
                ],
                "produces": [
                    "application/json"
                ],
                "tags": [
                    "系统模块"
                ],
                "summary": "菜单删除接口",
                "parameters": [
                    {
                        "type": "string",
                        "description": "入参",
                        "name": "id",
                        "in": "query"
                    }
                ],
                "responses": {
                    "200": {
                        "description": "OK",
                        "schema": {
                            "$ref": "#/definitions/github_com_Struggle-Rabbit_CampusLogistics_pkg_utils.SuccessResponse"
                        }
                    },
                    "400": {
                        "description": "Bad Request",
                        "schema": {
                            "$ref": "#/definitions/github_com_Struggle-Rabbit_CampusLogistics_pkg_utils.ErrResponse"
                        }
                    }
                }
            }
        },
        "/api/v1/menu/detail": {
            "get": {
                "description": "菜单详情查询",
                "consumes": [
                    "application/json"
                ],
                "produces": [
                    "application/json"
                ],
                "tags": [
                    "系统模块"
                ],
                "summary": "菜单详情接口",
                "parameters": [
                    {
                        "type": "string",
                        "description": "入参",
                        "name": "id",
                        "in": "query",
                        "required": true
                    }
                ],
                "responses": {
                    "200": {
                        "description": "OK",
                        "schema": {
                            "$ref": "#/definitions/github_com_Struggle-Rabbit_CampusLogistics_pkg_utils.SuccessResponse"
                        }
                    },
                    "400": {
                        "description": "Bad Request",
                        "schema": {
                            "$ref": "#/definitions/github_com_Struggle-Rabbit_CampusLogistics_pkg_utils.ErrResponse"
                        }
                    }
                }
            }
        },
        "/api/v1/menu/listPage": {
            "get": {
                "description": "菜单查询",
                "consumes": [
                    "application/json"
                ],
                "produces": [
                    "application/json"
                ],
                "tags": [
                    "系统模块"
                ],
                "summary": "菜单查询接口",
                "parameters": [
                    {
                        "type": "integer",
                        "description": "当前页",
                        "name": "currentPage",
                        "in": "query"
                    },
                    {
                        "type": "string",
                        "description": "菜单名称",
                        "name": "name",
                        "in": "query"
                    },
                    {
                        "type": "integer",
                        "description": "每页条数",
                        "name": "pageSize",
                        "in": "query"
                    },
                    {
                        "type": "string",
                        "name": "parent_id",
                        "in": "query"
                    },
                    {
                        "type": "string",
                        "description": "权限标识 sys:user:list",
                        "name": "perms",
                        "in": "query"
                    },
                    {
                        "type": "integer",
                        "description": "状态",
                        "name": "status",
                        "in": "query"
                    },
                    {
                        "type": "integer",
                        "description": "1目录2菜单3按钮",
                        "name": "type",
                        "in": "query"
                    }
                ],
                "responses": {
                    "200": {
                        "description": "OK",
                        "schema": {
                            "$ref": "#/definitions/github_com_Struggle-Rabbit_CampusLogistics_pkg_utils.SuccessResponse"
                        }
                    },
                    "400": {
                        "description": "Bad Request",
                        "schema": {
                            "$ref": "#/definitions/github_com_Struggle-Rabbit_CampusLogistics_pkg_utils.ErrResponse"
                        }
                    }
                }
            }
        },
        "/api/v1/menu/update": {
            "post": {
                "description": "菜单更新",
                "consumes": [
                    "application/json"
                ],
                "produces": [
                    "application/json"
                ],
                "tags": [
                    "系统模块"
                ],
                "summary": "菜单更新接口",
                "parameters": [
                    {
                        "description": "入参",
                        "name": "data",
                        "in": "body",
                        "schema": {
                            "$ref": "#/definitions/github_com_Struggle-Rabbit_CampusLogistics_api_dto.UpdateMenuReq"
                        }
                    }
                ],
                "responses": {
                    "200": {
                        "description": "OK",
                        "schema": {
                            "$ref": "#/definitions/github_com_Struggle-Rabbit_CampusLogistics_pkg_utils.SuccessResponse"
                        }
                    },
                    "400": {
                        "description": "Bad Request",
                        "schema": {
                            "$ref": "#/definitions/github_com_Struggle-Rabbit_CampusLogistics_pkg_utils.ErrResponse"
                        }
                    }
                }
            }
        },
        "/api/v1/register": {
            "post": {
                "description": "注册新用户",
                "consumes": [
                    "application/json"
                ],
                "produces": [
                    "application/json"
                ],
                "tags": [
                    "用户管理"
                ],
                "summary": "用户注册接口",
                "parameters": [
                    {
                        "description": "注册参数",
                        "name": "data",
                        "in": "body",
                        "required": true,
                        "schema": {
                            "$ref": "#/definitions/github_com_Struggle-Rabbit_CampusLogistics_api_dto.RegisterReq"
                        }
                    }
                ],
                "responses": {
                    "200": {
                        "description": "OK",
                        "schema": {
                            "$ref": "#/definitions/github_com_Struggle-Rabbit_CampusLogistics_pkg_utils.SuccessResponse"
                        }
                    },
                    "400": {
                        "description": "Bad Request",
                        "schema": {
                            "$ref": "#/definitions/github_com_Struggle-Rabbit_CampusLogistics_pkg_utils.ErrResponse"
                        }
                    }
                }
            }
        },
        "/api/v1/role/add": {
            "post": {
                "description": "角色创建",
                "consumes": [
                    "application/json"
                ],
                "produces": [
                    "application/json"
                ],
                "tags": [
                    "系统模块"
                ],
                "summary": "角色创建接口",
                "parameters": [
                    {
                        "description": "入参",
                        "name": "data",
                        "in": "body",
                        "required": true,
                        "schema": {
                            "$ref": "#/definitions/github_com_Struggle-Rabbit_CampusLogistics_api_dto.CreateRoleReq"
                        }
                    }
                ],
                "responses": {
                    "200": {
                        "description": "OK",
                        "schema": {
                            "$ref": "#/definitions/github_com_Struggle-Rabbit_CampusLogistics_pkg_utils.SuccessResponse"
                        }
                    },
                    "400": {
                        "description": "Bad Request",
                        "schema": {
                            "$ref": "#/definitions/github_com_Struggle-Rabbit_CampusLogistics_pkg_utils.ErrResponse"
                        }
                    }
                }
            }
        },
        "/api/v1/role/del": {
            "post": {
                "description": "角色删除",
                "consumes": [
                    "application/json"
                ],
                "produces": [
                    "application/json"
                ],
                "tags": [
                    "系统模块"
                ],
                "summary": "角色删除接口",
                "parameters": [
                    {
                        "description": "入参",
                        "name": "data",
                        "in": "body",
                        "required": true,
                        "schema": {
                            "type": "object",
                            "additionalProperties": true
                        }
                    }
                ],
                "responses": {
                    "200": {
                        "description": "OK",
                        "schema": {
                            "$ref": "#/definitions/github_com_Struggle-Rabbit_CampusLogistics_pkg_utils.SuccessResponse"
                        }
                    },
                    "400": {
                        "description": "Bad Request",
                        "schema": {
                            "$ref": "#/definitions/github_com_Struggle-Rabbit_CampusLogistics_pkg_utils.ErrResponse"
                        }
                    }
                }
            }
        },
        "/api/v1/role/detail": {
            "get": {
                "description": "角色详情查询",
                "consumes": [
                    "application/json"
                ],
                "produces": [
                    "application/json"
                ],
                "tags": [
                    "系统模块"
                ],
                "summary": "角色详情查询接口",
                "parameters": [
                    {
                        "type": "string",
                        "description": "入参",
                        "name": "id",
                        "in": "query",
                        "required": true
                    }
                ],
                "responses": {
                    "200": {
                        "description": "OK",
                        "schema": {
                            "$ref": "#/definitions/github_com_Struggle-Rabbit_CampusLogistics_pkg_utils.SuccessResponse"
                        }
                    },
                    "400": {
                        "description": "Bad Request",
                        "schema": {
                            "$ref": "#/definitions/github_com_Struggle-Rabbit_CampusLogistics_pkg_utils.ErrResponse"
                        }
                    }
                }
            }
        },
        "/api/v1/role/list": {
            "get": {
                "description": "角色列表查询",
                "consumes": [
                    "application/json"
                ],
                "produces": [
                    "application/json"
                ],
                "tags": [
                    "系统模块"
                ],
                "summary": "角色列表查询接口",
                "parameters": [
                    {
                        "type": "integer",
                        "description": "当前页",
                        "name": "currentPage",
                        "in": "query"
                    },
                    {
                        "type": "integer",
                        "description": "每页条数",
                        "name": "pageSize",
                        "in": "query"
                    },
                    {
                        "type": "string",
                        "name": "role_name",
                        "in": "query"
                    },
                    {
                        "type": "string",
                        "name": "status",
                        "in": "query"
                    }
                ],
                "responses": {
                    "200": {
                        "description": "OK",
                        "schema": {
                            "$ref": "#/definitions/github_com_Struggle-Rabbit_CampusLogistics_pkg_utils.SuccessResponse"
                        }
                    },
                    "400": {
                        "description": "Bad Request",
                        "schema": {
                            "$ref": "#/definitions/github_com_Struggle-Rabbit_CampusLogistics_pkg_utils.ErrResponse"
                        }
                    }
                }
            }
        },
        "/api/v1/role/listPage": {
            "get": {
                "description": "角色分页查询",
                "consumes": [
                    "application/json"
                ],
                "produces": [
                    "application/json"
                ],
                "tags": [
                    "系统模块"
                ],
                "summary": "角色分页查询接口",
                "parameters": [
                    {
                        "type": "integer",
                        "description": "当前页",
                        "name": "currentPage",
                        "in": "query"
                    },
                    {
                        "type": "integer",
                        "description": "每页条数",
                        "name": "pageSize",
                        "in": "query"
                    },
                    {
                        "type": "string",
                        "name": "role_name",
                        "in": "query"
                    },
                    {
                        "type": "string",
                        "name": "status",
                        "in": "query"
                    }
                ],
                "responses": {
                    "200": {
                        "description": "OK",
                        "schema": {
                            "$ref": "#/definitions/github_com_Struggle-Rabbit_CampusLogistics_pkg_utils.SuccessResponse"
                        }
                    },
                    "400": {
                        "description": "Bad Request",
                        "schema": {
                            "$ref": "#/definitions/github_com_Struggle-Rabbit_CampusLogistics_pkg_utils.ErrResponse"
                        }
                    }
                }
            }
        },
        "/api/v1/role/update": {
            "post": {
                "description": "角色修改",
                "consumes": [
                    "application/json"
                ],
                "produces": [
                    "application/json"
                ],
                "tags": [
                    "系统模块"
                ],
                "summary": "角色修改接口",
                "parameters": [
                    {
                        "description": "入参",
                        "name": "data",
                        "in": "body",
                        "required": true,
                        "schema": {
                            "$ref": "#/definitions/github_com_Struggle-Rabbit_CampusLogistics_api_dto.UpdateRoleReq"
                        }
                    }
                ],
                "responses": {
                    "200": {
                        "description": "OK",
                        "schema": {
                            "$ref": "#/definitions/github_com_Struggle-Rabbit_CampusLogistics_pkg_utils.SuccessResponse"
                        }
                    },
                    "400": {
                        "description": "Bad Request",
                        "schema": {
                            "$ref": "#/definitions/github_com_Struggle-Rabbit_CampusLogistics_pkg_utils.ErrResponse"
                        }
                    }
                }
            }
        },
        "/api/v1/user/del": {
            "post": {
                "description": "删除用户",
                "consumes": [
                    "application/json"
                ],
                "produces": [
                    "application/json"
                ],
                "tags": [
                    "用户管理"
                ],
                "summary": "用户删除接口",
                "parameters": [
                    {
                        "description": "入参",
                        "name": "id",
                        "in": "body",
                        "required": true,
                        "schema": {
                            "type": "string"
                        }
                    }
                ],
                "responses": {
                    "200": {
                        "description": "OK",
                        "schema": {
                            "$ref": "#/definitions/github_com_Struggle-Rabbit_CampusLogistics_pkg_utils.SuccessResponse"
                        }
                    },
                    "400": {
                        "description": "Bad Request",
                        "schema": {
                            "$ref": "#/definitions/github_com_Struggle-Rabbit_CampusLogistics_pkg_utils.ErrResponse"
                        }
                    }
                }
            }
        },
        "/api/v1/user/detail": {
            "get": {
                "description": "用户详情查询",
                "consumes": [
                    "application/json"
                ],
                "produces": [
                    "application/json"
                ],
                "tags": [
                    "用户管理"
                ],
                "summary": "用户详情查询接口",
                "parameters": [
                    {
                        "type": "string",
                        "description": "入参",
                        "name": "id",
                        "in": "query",
                        "required": true
                    }
                ],
                "responses": {
                    "200": {
                        "description": "OK",
                        "schema": {
                            "$ref": "#/definitions/github_com_Struggle-Rabbit_CampusLogistics_pkg_utils.SuccessResponse"
                        }
                    },
                    "400": {
                        "description": "Bad Request",
                        "schema": {
                            "$ref": "#/definitions/github_com_Struggle-Rabbit_CampusLogistics_pkg_utils.ErrResponse"
                        }
                    }
                }
            }
        },
        "/api/v1/user/getUserPermission": {
            "get": {
                "description": "用户菜单权限查询",
                "consumes": [
                    "application/json"
                ],
                "produces": [
                    "application/json"
                ],
                "tags": [
                    "用户管理"
                ],
                "summary": "用户菜单权限查询接口",
                "responses": {
                    "200": {
                        "description": "OK",
                        "schema": {
                            "$ref": "#/definitions/github_com_Struggle-Rabbit_CampusLogistics_pkg_utils.SuccessResponse"
                        }
                    },
                    "400": {
                        "description": "Bad Request",
                        "schema": {
                            "$ref": "#/definitions/github_com_Struggle-Rabbit_CampusLogistics_pkg_utils.ErrResponse"
                        }
                    }
                }
            }
        },
        "/api/v1/user/listPage": {
            "get": {
                "description": "用户分页查询",
                "consumes": [
                    "application/json"
                ],
                "produces": [
                    "application/json"
                ],
                "tags": [
                    "用户管理"
                ],
                "summary": "用户分页查询接口",
                "parameters": [
                    {
                        "type": "integer",
                        "description": "当前页",
                        "name": "currentPage",
                        "in": "query"
                    },
                    {
                        "type": "string",
                        "name": "mobile",
                        "in": "query"
                    },
                    {
                        "type": "string",
                        "name": "name",
                        "in": "query"
                    },
                    {
                        "type": "integer",
                        "description": "每页条数",
                        "name": "pageSize",
                        "in": "query"
                    },
                    {
                        "type": "string",
                        "name": "status",
                        "in": "query"
                    },
                    {
                        "type": "string",
                        "name": "userType",
                        "in": "query"
                    }
                ],
                "responses": {
                    "200": {
                        "description": "OK",
                        "schema": {
                            "$ref": "#/definitions/github_com_Struggle-Rabbit_CampusLogistics_pkg_utils.SuccessResponse"
                        }
                    },
                    "400": {
                        "description": "Bad Request",
                        "schema": {
                            "$ref": "#/definitions/github_com_Struggle-Rabbit_CampusLogistics_pkg_utils.ErrResponse"
                        }
                    }
                }
            },
            "post": {
                "description": "用户信息更新",
                "consumes": [
                    "application/json"
                ],
                "produces": [
                    "application/json"
                ],
                "tags": [
                    "用户管理"
                ],
                "summary": "用户更新接口",
                "parameters": [
                    {
                        "description": "入参",
                        "name": "data",
                        "in": "body",
                        "required": true,
                        "schema": {
                            "$ref": "#/definitions/github_com_Struggle-Rabbit_CampusLogistics_api_dto.UserUpdateReq"
                        }
                    }
                ],
                "responses": {
                    "200": {
                        "description": "OK",
                        "schema": {
                            "$ref": "#/definitions/github_com_Struggle-Rabbit_CampusLogistics_pkg_utils.SuccessResponse"
                        }
                    },
                    "400": {
                        "description": "Bad Request",
                        "schema": {
                            "$ref": "#/definitions/github_com_Struggle-Rabbit_CampusLogistics_pkg_utils.ErrResponse"
                        }
                    }
                }
            }
        }
    },
    "definitions": {
        "github_com_Struggle-Rabbit_CampusLogistics_api_dto.CreateMenuReq": {
            "type": "object",
            "required": [
                "name",
                "perms",
                "status",
                "type"
            ],
            "properties": {
                "component": {
                    "description": "前端组件",
                    "type": "string"
                },
                "description": {
                    "description": "描述",
                    "type": "string"
                },
                "icon": {
                    "type": "string"
                },
                "name": {
                    "description": "菜单名称",
                    "type": "string"
                },
                "parent_id": {
                    "type": "string"
                },
                "path": {
                    "description": "路由",
                    "type": "string"
                },
                "perms": {
                    "description": "权限标识 sys:user:list",
                    "type": "string"
                },
                "sort": {
                    "type": "integer"
                },
                "status": {
                    "description": "状态",
                    "type": "integer"
                },
                "type": {
                    "description": "1目录2菜单3按钮",
                    "type": "integer"
                }
            }
        },
        "github_com_Struggle-Rabbit_CampusLogistics_api_dto.CreateRoleReq": {
            "type": "object",
            "required": [
                "role_code",
                "role_name",
                "status"
            ],
            "properties": {
                "description": {
                    "type": "string"
                },
                "is_built_in": {
                    "type": "integer"
                },
                "role_code": {
                    "type": "string"
                },
                "role_name": {
                    "type": "string"
                },
                "status": {
                    "type": "string"
                }
            }
        },
        "github_com_Struggle-Rabbit_CampusLogistics_api_dto.LoginReq": {
            "type": "object",
            "required": [
                "account",
                "password"
            ],
            "properties": {
                "account": {
                    "type": "string",
                    "example": "13811111111"
                },
                "password": {
                    "type": "string",
                    "example": "12345678"
                }
            }
        },
        "github_com_Struggle-Rabbit_CampusLogistics_api_dto.RegisterReq": {
            "type": "object",
            "required": [
                "mobile",
                "name",
                "password",
                "userType"
            ],
            "properties": {
                "mobile": {
                    "type": "string",
                    "example": "13811111111"
                },
                "name": {
                    "type": "string",
                    "example": "张三"
                },
                "password": {
                    "type": "string",
                    "maxLength": 20,
                    "minLength": 8,
                    "example": "12345678"
                },
                "userType": {
                    "type": "string",
                    "enum": [
                        "00",
                        "01",
                        "02"
                    ],
                    "example": "02"
                }
            }
        },
        "github_com_Struggle-Rabbit_CampusLogistics_api_dto.UpdateMenuReq": {
            "type": "object",
            "required": [
                "id"
            ],
            "properties": {
                "component": {
                    "description": "前端组件",
                    "type": "string"
                },
                "description": {
                    "description": "描述",
                    "type": "string"
                },
                "icon": {
                    "type": "string"
                },
                "id": {
                    "type": "string"
                },
                "name": {
                    "description": "菜单名称",
                    "type": "string"
                },
                "parent_id": {
                    "type": "string"
                },
                "path": {
                    "description": "路由",
                    "type": "string"
                },
                "perms": {
                    "description": "权限标识 sys:user:list",
                    "type": "string"
                },
                "sort": {
                    "type": "integer"
                },
                "status": {
                    "description": "状态",
                    "type": "integer"
                },
                "type": {
                    "description": "1目录2菜单3按钮",
                    "type": "integer"
                }
            }
        },
        "github_com_Struggle-Rabbit_CampusLogistics_api_dto.UpdateRoleReq": {
            "type": "object",
            "required": [
                "id"
            ],
            "properties": {
                "description": {
                    "type": "string"
                },
                "id": {
                    "type": "string"
                },
                "is_built_in": {
                    "type": "integer"
                },
                "role_code": {
                    "type": "string"
                },
                "role_name": {
                    "type": "string"
                },
                "status": {
                    "type": "string"
                }
            }
        },
        "github_com_Struggle-Rabbit_CampusLogistics_api_dto.UserUpdateReq": {
            "type": "object",
            "properties": {
                "avatar": {
                    "description": "头像URL",
                    "type": "string"
                },
                "id": {
                    "type": "string"
                },
                "mobile": {
                    "description": "手机号（唯一）",
                    "type": "string"
                },
                "name": {
                    "description": "姓名",
                    "type": "string"
                },
                "status": {
                    "description": "状态：1-启用 2-禁用",
                    "type": "integer"
                },
                "user_code": {
                    "description": "学号/工号（唯一）",
                    "type": "string"
                },
                "user_type": {
                    "description": "用户类型: 00-管理员  01-职工  02-学生",
                    "type": "string"
                }
            }
        },
        "github_com_Struggle-Rabbit_CampusLogistics_pkg_utils.ErrResponse": {
            "type": "object",
            "properties": {
                "code": {
                    "type": "integer",
                    "example": 400
                },
                "err": {
                    "type": "object"
                },
                "msg": {
                    "type": "string",
                    "example": "失败"
                }
            }
        },
        "github_com_Struggle-Rabbit_CampusLogistics_pkg_utils.SuccessResponse": {
            "type": "object",
            "properties": {
                "code": {
                    "type": "integer",
                    "example": 200
                },
                "data": {
                    "type": "object"
                },
                "msg": {
                    "type": "string",
                    "example": "操作成功"
                }
            }
        }
    },
    "securityDefinitions": {
        "ApiKeyAuth": {
            "description": "Type \"Bearer\" followed by a space and JWT token.",
            "type": "apiKey",
            "name": "Authorization",
            "in": "header"
        }
    }
}